{"matchId":"4f290869-4edd-4661-b462-0ef011ebc940.nakama-0","matchFile":"4f290869-4edd-4661-b462-0ef011ebc940_nakama-0.json","mapId":"AmbroseValley","date":"2026-02-10","durationMs":461,"humans":1,"bots":0,"players":[{"userId":"f4e072fa-b7af-4761-b567-1d95b7ad0108","isBot":false,"positions":[{"t":0,"x":-295.32,"z":-338.2,"px":84.97,"py":870.63,"event":"Position"},{"t":15,"x":-279.55,"z":-325.65,"px":102.91,"py":856.35,"event":"Position"},{"t":20,"x":-270.94,"z":-327.69,"px":112.7,"py":858.67,"event":"Position"},{"t":25,"x":-261.73,"z":-328.25,"px":123.19,"py":859.3,"event":"Position"},{"t":30,"x":-246.89,"z":-338.66,"px":140.07,"py":871.15,"event":"Position"},{"t":35,"x":-239.23,"z":-314.33,"px":148.79,"py":843.47,"event":"Position"},{"t":40,"x":-212.63,"z":-298.09,"px":179.05,"py":824.99,"event":"Position"},{"t":50,"x":-200.33,"z":-298.69,"px":193.05,"py":825.68,"event":"Position"},{"t":55,"x":-198.75,"z":-304.96,"px":194.84,"py":832.81,"event":"Position"},{"t":65,"x":-196.32,"z":-306.97,"px":197.61,"py":835.09,"event":"Position"},{"t":70,"x":-174.76,"z":-316.56,"px":222.14,"py":846.01,"event":"Position"},{"t":75,"x":-167.62,"z":-328.97,"px":230.26,"py":860.13,"event":"Position"},{"t":80,"x":-166.78,"z":-332.56,"px":231.21,"py":864.21,"event":"Position"},{"t":86,"x":-170.77,"z":-340.78,"px":226.68,"py":873.56,"event":"Position"},{"t":91,"x":-179.12,"z":-331.48,"px":217.18,"py":862.99,"event":"Position"},{"t":96,"x":-171.78,"z":-316.65,"px":225.53,"py":846.11,"event":"Position"},{"t":106,"x":-187.56,"z":-324.09,"px":207.57,"py":854.58,"event":"Position"},{"t":111,"x":-205.79,"z":-328.05,"px":186.84,"py":859.08,"event":"Position"},{"t":116,"x":-195.26,"z":-315.76,"px":198.82,"py":845.1,"event":"Position"},{"t":121,"x":-181.02,"z":-314.83,"px":215.01,"py":844.04,"event":"Position"},{"t":126,"x":-172.04,"z":-316.31,"px":225.23,"py":845.72,"event":"Position"},{"t":131,"x":-179.31,"z":-310.6,"px":216.96,"py":839.23,"event":"Position"},{"t":136,"x":-186.06,"z":-315.54,"px":209.28,"py":844.85,"event":"Position"},{"t":141,"x":-174.13,"z":-313.87,"px":222.86,"py":842.94,"event":"Position"},{"t":146,"x":-165.58,"z":-315.56,"px":232.59,"py":844.87,"event":"Position"},{"t":151,"x":-163.56,"z":-317.38,"px":234.88,"py":846.94,"event":"Position"},{"t":161,"x":-166.76,"z":-307.88,"px":231.25,"py":836.13,"event":"Position"},{"t":166,"x":-172.0,"z":-312.53,"px":225.28,"py":841.42,"event":"Position"},{"t":171,"x":-185.58,"z":-326.31,"px":209.83,"py":857.1,"event":"Position"},{"t":176,"x":-182.11,"z":-324.91,"px":213.78,"py":855.51,"event":"Position"},{"t":181,"x":-172.37,"z":-320.03,"px":224.86,"py":849.95,"event":"Position"},{"t":186,"x":-155.68,"z":-338.49,"px":243.85,"py":870.95,"event":"Position"},{"t":191,"x":-141.5,"z":-318.74,"px":259.99,"py":848.49,"event":"Position"},{"t":196,"x":-132.6,"z":-304.63,"px":270.1,"py":832.43,"event":"Position"},{"t":201,"x":-159.62,"z":-309.15,"px":239.37,"py":837.58,"event":"Position"},{"t":206,"x":-169.33,"z":-310.91,"px":228.31,"py":839.58,"event":"Position"},{"t":216,"x":-180.19,"z":-318.87,"px":215.96,"py":848.63,"event":"Position"},{"t":221,"x":-197.85,"z":-307.67,"px":195.87,"py":835.89,"event":"Position"},{"t":226,"x":-213.81,"z":-318.81,"px":177.71,"py":848.56,"event":"Position"},{"t":231,"x":-215.84,"z":-323.26,"px":175.4,"py":853.63,"event":"Position"},{"t":236,"x":-225.98,"z":-327.78,"px":163.87,"py":858.78,"event":"Position"},{"t":241,"x":-221.72,"z":-339.7,"px":168.7,"py":872.34,"event":"Position"},{"t":246,"x":-227.64,"z":-338.81,"px":161.97,"py":871.32,"event":"Position"},{"t":251,"x":-222.19,"z":-321.41,"px":168.18,"py":851.52,"event":"Position"},{"t":256,"x":-216.0,"z":-328.13,"px":175.22,"py":859.17,"event":"Position"},{"t":262,"x":-210.85,"z":-334.78,"px":181.07,"py":866.74,"event":"Position"},{"t":267,"x":-201.26,"z":-322.84,"px":191.98,"py":853.15,"event":"Position"},{"t":277,"x":-196.02,"z":-324.85,"px":197.95,"py":855.44,"event":"Position"},{"t":282,"x":-212.96,"z":-318.91,"px":178.68,"py":848.68,"event":"Position"},{"t":287,"x":-214.15,"z":-305.8,"px":177.32,"py":833.77,"event":"Position"},{"t":292,"x":-203.66,"z":-265.2,"px":189.26,"py":787.57,"event":"Position"},{"t":297,"x":-201.4,"z":-224.79,"px":191.83,"py":741.59,"event":"Position"},{"t":302,"x":-184.81,"z":-200.59,"px":210.7,"py":714.06,"event":"Position"},{"t":307,"x":-165.39,"z":-174.96,"px":232.8,"py":684.9,"event":"Position"},{"t":312,"x":-144.18,"z":-180.95,"px":256.93,"py":691.71,"event":"Position"},{"t":317,"x":-125.85,"z":-164.08,"px":277.79,"py":672.52,"event":"Position"},{"t":322,"x":-109.95,"z":-141.17,"px":295.88,"py":646.45,"event":"Position"},{"t":327,"x":-104.01,"z":-111.43,"px":302.64,"py":612.62,"event":"Position"},{"t":332,"x":-102.42,"z":-94.6,"px":304.45,"py":593.46,"event":"Position"},{"t":337,"x":-77.94,"z":-98.4,"px":332.3,"py":597.78,"event":"Position"},{"t":342,"x":-101.07,"z":-87.71,"px":305.98,"py":585.63,"event":"Position"},{"t":347,"x":-103.17,"z":-56.36,"px":303.59,"py":549.95,"event":"Position"},{"t":352,"x":-104.63,"z":-46.15,"px":301.93,"py":538.34,"event":"Position"},{"t":357,"x":-111.28,"z":-40.12,"px":294.36,"py":531.48,"event":"Position"},{"t":362,"x":-109.68,"z":-40.21,"px":296.18,"py":531.58,"event":"Position"},{"t":367,"x":-106.77,"z":-37.05,"px":299.5,"py":527.99,"event":"Position"},{"t":372,"x":-101.14,"z":-44.95,"px":305.9,"py":536.97,"event":"Position"},{"t":377,"x":-109.94,"z":-37.51,"px":295.89,"py":528.51,"event":"Position"},{"t":382,"x":-116.77,"z":-31.69,"px":288.12,"py":521.89,"event":"Position"},{"t":387,"x":-102.71,"z":-7.33,"px":304.12,"py":494.17,"event":"Position"},{"t":392,"x":-89.4,"z":-4.46,"px":319.26,"py":490.91,"event":"Position"},{"t":397,"x":-84.17,"z":-4.21,"px":325.21,"py":490.62,"event":"Position"},{"t":402,"x":-58.74,"z":-0.23,"px":354.14,"py":486.1,"event":"Position"},{"t":407,"x":-40.18,"z":9.09,"px":375.26,"py":475.48,"event":"Position"},{"t":412,"x":-33.95,"z":26.42,"px":382.35,"py":455.78,"event":"Position"},{"t":417,"x":-27.42,"z":39.6,"px":389.78,"py":440.77,"event":"Position"},{"t":427,"x":-23.58,"z":38.43,"px":394.15,"py":442.1,"event":"Position"},{"t":432,"x":-26.2,"z":40.41,"px":391.17,"py":439.86,"event":"Position"},{"t":437,"x":-29.19,"z":39.55,"px":387.77,"py":440.83,"event":"Position"},{"t":443,"x":-33.16,"z":38.59,"px":383.25,"py":441.92,"event":"Position"},{"t":448,"x":-37.27,"z":37.39,"px":378.57,"py":443.29,"event":"Position"},{"t":453,"x":-41.3,"z":36.06,"px":373.99,"py":444.8,"event":"Position"},{"t":458,"x":-45.3,"z":34.54,"px":369.44,"py":446.53,"event":"Position"}],"events":[{"t":60,"x":-199.65,"z":-304.62,"px":193.83,"py":832.42,"event":"BotKill"},{"t":63,"x":-199.93,"z":-304.89,"px":193.5,"py":832.73,"event":"Loot"},{"t":64,"x":-199.93,"z":-304.89,"px":193.5,"py":832.73,"event":"Loot"},{"t":75,"x":-167.62,"z":-328.97,"px":230.26,"py":860.13,"event":"Loot"},{"t":86,"x":-170.77,"z":-340.78,"px":226.68,"py":873.56,"event":"Loot"},{"t":87,"x":-170.77,"z":-340.78,"px":226.68,"py":873.56,"event":"Loot"},{"t":219,"x":-190.98,"z":-319.25,"px":203.68,"py":849.07,"event":"Loot"},{"t":236,"x":-225.38,"z":-329.11,"px":164.54,"py":860.28,"event":"Loot"},{"t":247,"x":-227.64,"z":-338.81,"px":161.97,"py":871.32,"event":"Loot"},{"t":253,"x":-222.19,"z":-321.41,"px":168.18,"py":851.52,"event":"Loot"},{"t":273,"x":-198.87,"z":-322.01,"px":194.7,"py":852.21,"event":"BotKill"},{"t":275,"x":-199.09,"z":-321.85,"px":194.46,"py":852.02,"event":"Loot"},{"t":311,"x":-146.07,"z":-180.21,"px":254.78,"py":690.87,"event":"Loot"},{"t":355,"x":-114.94,"z":-39.87,"px":290.2,"py":531.19,"event":"Loot"},{"t":356,"x":-114.94,"z":-39.87,"px":290.2,"py":531.19,"event":"Loot"},{"t":360,"x":-113.29,"z":-37.01,"px":292.08,"py":527.94,"event":"Loot"},{"t":365,"x":-99.49,"z":-38.46,"px":307.78,"py":529.59,"event":"Loot"},{"t":371,"x":-100.42,"z":-42.1,"px":306.72,"py":533.73,"event":"Loot"},{"t":373,"x":-101.61,"z":-46.28,"px":305.36,"py":538.48,"event":"Loot"},{"t":388,"x":-102.14,"z":-6.43,"px":304.77,"py":493.15,"event":"Loot"},{"t":461,"x":-47.6,"z":32.44,"px":366.82,"py":448.93,"event":"BotKilled"}],"counts":{"Position":83,"BotKill":2,"Loot":18,"BotKilled":1}}],"stats":{"Position":83,"BotKill":2,"Loot":18,"BotKilled":1}}